davil/__init__.py
davil/confusion.py
davil/fs.py
davil/graph.py
davil/h5.py
davil/lists.py
davil/log.py
davil/nutil.py
davil/paths.py
davil/pickle.py
davil/plot.py
davil/sampling.py
davil/save.py
davil/sort.py
davil/strings.py
davil/timings.py
davil/types.py
davil-0.0.2.dist-info/LICENSE
davil-0.0.2.dist-info/METADATA
davil-0.0.2.dist-info/WHEEL
davil-0.0.2.dist-info/top_level.txt
davil-0.0.2.dist-info/RECORD
