Metadata-Version: 2.1
Name: davil
Version: 0.0.2
Summary: Various Utils for no specific purpose.
Home-page: https://github.com/Treiblesschorle/davil
Author: David Kolb
Author-email: david_kolb@t-online.de
License: UNKNOWN
Platform: UNKNOWN
Classifier: Programming Language :: Python :: 3
Classifier: License :: OSI Approved :: MIT License
Classifier: Operating System :: OS Independent
Requires-Python: >=3.6
Requires-Dist: numpy (==1.18.1)
Requires-Dist: scipy (==1.4.1)
Requires-Dist: sty (==1.0.0b12)
Requires-Dist: matplotlib (==3.1.3)
